piper_control/__init__.py
piper_control/_git_hash.py
piper_control/_version.py
piper_control/collision_checking.py
piper_control/gravity_compensation.py
piper_control/piper_connect.py
piper_control/piper_connect_main.py
piper_control/piper_control.py
piper_control/piper_init.py
piper_control/piper_interface.py
piper_control/models/piper_grav_comp.xml
piper_control/scripts/__init__.py
piper_control/scripts/generate_samples.py
piper_control/scripts/run_gravity_compensation.py
piper_control/scripts/set_collision_protection.py
piper_control-1.3.1.dist-info/licenses/LICENSE
piper_control-1.3.1.dist-info/METADATA
piper_control-1.3.1.dist-info/WHEEL
piper_control-1.3.1.dist-info/entry_points.txt
piper_control-1.3.1.dist-info/top_level.txt
piper_control-1.3.1.dist-info/RECORD
