Metadata-Version: 2.4
Name: piper_control
Version: 1.3.1
Summary: A wrapper around piper_sdk for controlling AgileX Piper arms.
Author-email: Reimagine Robotics <info@reimaginerobotics.ai>
License-Expression: MIT
Project-URL: Repository, https://github.com/Reimagine-Robotics/piper_control
Requires-Python: >=3.10
License-File: LICENSE
Requires-Dist: numpy
Requires-Dist: packaging
Requires-Dist: piper-sdk>=0.2.19
Provides-Extra: gravity
Requires-Dist: mujoco; extra == "gravity"
Requires-Dist: scipy; extra == "gravity"
Dynamic: license-file
